hugo_nbconvert/__main__.py
hugo_nbconvert/date.py
hugo_nbconvert/glob_hugo_ipynb.py
hugo_nbconvert/global_config.py
hugo_nbconvert/hugo_fix.py
hugo_nbconvert/main.py
hugo_nbconvert/markdown_convert.py
hugo_nbconvert/markdown_processor.py
hugo_nbconvert/new.py
hugo_nbconvert/resource.py
hugo_nbconvert/run.py
hugo_nbconvert/tools.py
hugo_nbconvert-2025.5.24.3.dist-info/METADATA
hugo_nbconvert-2025.5.24.3.dist-info/WHEEL
hugo_nbconvert-2025.5.24.3.dist-info/entry_points.txt
hugo_nbconvert-2025.5.24.3.dist-info/licenses/LICENSE
hugo_nbconvert-2025.5.24.3.dist-info/RECORD
