Metadata-Version: 2.4
Name: hugo-nbconvert
Version: 2025.5.24.3
Summary: convenient tools for intergrating jupyter notebooks with hugo
Project-URL: Repository, https://github.com/soda92/hugo-nbconvert
License-File: LICENSE
Requires-Python: >=3.11
Requires-Dist: hugo>=0.147.2
Requires-Dist: jupyter>=1.1.1
Requires-Dist: nbconvert>=7.16.6
Requires-Dist: sodatools>=2025.2.16.0
Requires-Dist: watchdog>=6.0.0
